parl/__init__.py
parl/algorithms/__init__.py
parl/algorithms/fluid/__init__.py
parl/algorithms/fluid/a3c.py
parl/algorithms/fluid/ddpg.py
parl/algorithms/fluid/ddqn.py
parl/algorithms/fluid/dqn.py
parl/algorithms/fluid/maddpg.py
parl/algorithms/fluid/policy_gradient.py
parl/algorithms/fluid/ppo.py
parl/algorithms/fluid/qmix.py
parl/algorithms/fluid/sac.py
parl/algorithms/fluid/td3.py
parl/algorithms/fluid/impala/__init__.py
parl/algorithms/fluid/impala/impala.py
parl/algorithms/fluid/impala/vtrace.py
parl/algorithms/paddle/__init__.py
parl/algorithms/paddle/a2c.py
parl/algorithms/paddle/cql.py
parl/algorithms/paddle/ddpg.py
parl/algorithms/paddle/ddqn.py
parl/algorithms/paddle/dqn.py
parl/algorithms/paddle/maddpg.py
parl/algorithms/paddle/oac.py
parl/algorithms/paddle/policy_gradient.py
parl/algorithms/paddle/ppo.py
parl/algorithms/paddle/qmix.py
parl/algorithms/paddle/sac.py
parl/algorithms/paddle/td3.py
parl/algorithms/paddle/impala/__init__.py
parl/algorithms/paddle/impala/impala.py
parl/algorithms/paddle/impala/vtrace.py
parl/algorithms/torch/__init__.py
parl/algorithms/torch/a2c.py
parl/algorithms/torch/coma.py
parl/algorithms/torch/cql.py
parl/algorithms/torch/ddpg.py
parl/algorithms/torch/ddqn.py
parl/algorithms/torch/dqn.py
parl/algorithms/torch/dt.py
parl/algorithms/torch/iql.py
parl/algorithms/torch/maddpg.py
parl/algorithms/torch/mappo.py
parl/algorithms/torch/oac.py
parl/algorithms/torch/policy_gradient.py
parl/algorithms/torch/ppo.py
parl/algorithms/torch/qmix.py
parl/algorithms/torch/sac.py
parl/algorithms/torch/td3.py
parl/core/__init__.py
parl/core/agent_base.py
parl/core/algorithm_base.py
parl/core/model_base.py
parl/core/fluid/__init__.py
parl/core/fluid/agent.py
parl/core/fluid/algorithm.py
parl/core/fluid/model.py
parl/core/fluid/model_helper.py
parl/core/fluid/policy_distribution.py
parl/core/fluid/layers/__init__.py
parl/core/fluid/layers/attr_holder.py
parl/core/fluid/layers/layer_wrappers.py
parl/core/fluid/plutils/__init__.py
parl-2.2.1.dist-info/LICENSE
parl-2.2.1.dist-info/METADATA
parl-2.2.1.dist-info/WHEEL
parl-2.2.1.dist-info/entry_points.txt
parl-2.2.1.dist-info/top_level.txt
parl-2.2.1.dist-info/RECORD
