Metadata-Version: 2.1
Name: parl
Version: 2.2.1
Summary: Reinforcement Learning Framework
Home-page: https://github.com/PaddlePaddle/PARL
Classifier: Intended Audience :: Developers
Classifier: License :: OSI Approved :: Apache Software License
Classifier: Operating System :: OS Independent
Classifier: Programming Language :: Python :: 3.5
Classifier: Programming Language :: Python :: 3.6
Classifier: Programming Language :: Python :: 3.7
Classifier: Programming Language :: Python :: 3.8
Classifier: Programming Language :: Python :: 3.9
License-File: LICENSE
Requires-Dist: termcolor (>=1.1.0)
Requires-Dist: scipy (>=1.0.0)
Requires-Dist: tensorboardX (==2.5)
Requires-Dist: tensorboard (<=2.11.0)
Requires-Dist: flask (>=1.0.4)
Requires-Dist: click
Requires-Dist: psutil (>=5.6.2)
Requires-Dist: flask-cors
Requires-Dist: requests
Requires-Dist: grpcio (==1.37.0)
Requires-Dist: protobuf (<=3.20.0,>=3.14.0)
Requires-Dist: pynvml
Requires-Dist: cloudpickle (==1.3.0) ; python_version < "3"
Requires-Dist: pyzmq (==18.1.1) ; python_version < "3.9"
Requires-Dist: cloudpickle (==1.6.0) ; python_version >= "3"
Requires-Dist: pyzmq (==22.3.0) ; python_version >= "3.9"
